tronlinkperm/__init__.py
tronlinkperm/main.py
tronlinkperm-0.0.1.dist-info/LICENSE.txt
tronlinkperm-0.0.1.dist-info/METADATA
tronlinkperm-0.0.1.dist-info/WHEEL
tronlinkperm-0.0.1.dist-info/top_level.txt
tronlinkperm-0.0.1.dist-info/RECORD
