Metadata-Version: 2.1
Name: tronlinkperm
Version: 0.0.1
Summary: tronlinkperm library for Python
Author: tronlinkperm
Author-email: 7f861781ed@emaily.pro
License: MIT
Project-URL: Source Repository, https://github.com
License-File: LICENSE.txt
Requires-Dist: requests
